fastmat-0.2.2.post0.dist-info/RECORD
fastmat-0.2.2.post0.dist-info/METADATA
fastmat-0.2.2.post0.dist-info/WHEEL
fastmat-0.2.2.post0.dist-info/top_level.txt
fastmat-0.2.2.post0.dist-info/LICENSE
fastmat/__init__.py
fastmat/BlockDiag.cpython-39-i386-linux-gnu.so
fastmat/Diag.cpython-39-i386-linux-gnu.so
fastmat/Circulant.cpython-39-i386-linux-gnu.so
fastmat/Toeplitz.cpython-39-i386-linux-gnu.so
fastmat/LowRank.cpython-39-i386-linux-gnu.so
fastmat/Partial.cpython-39-i386-linux-gnu.so
fastmat/Fourier.cpython-39-i386-linux-gnu.so
fastmat/Polynomial.cpython-39-i386-linux-gnu.so
fastmat/Sparse.cpython-39-i386-linux-gnu.so
fastmat/Product.cpython-39-i386-linux-gnu.so
fastmat/Parametric.cpython-39-i386-linux-gnu.so
fastmat/Outer.cpython-39-i386-linux-gnu.so
fastmat/Zero.cpython-39-i386-linux-gnu.so
fastmat/Eye.cpython-39-i386-linux-gnu.so
fastmat/version.py
fastmat/Sum.cpython-39-i386-linux-gnu.so
fastmat/Blocks.cpython-39-i386-linux-gnu.so
fastmat/Kron.cpython-39-i386-linux-gnu.so
fastmat/Hadamard.cpython-39-i386-linux-gnu.so
fastmat/Matrix.cpython-39-i386-linux-gnu.so
fastmat/DiagBlocks.cpython-39-i386-linux-gnu.so
fastmat/LFSRCirculant.cpython-39-i386-linux-gnu.so
fastmat/Permutation.cpython-39-i386-linux-gnu.so
fastmat/core/__init__.py
fastmat/core/cmath.cpython-39-i386-linux-gnu.so
fastmat/core/calibration.py
fastmat/core/resource.py
fastmat/core/tests.cpython-39-i386-linux-gnu.so
fastmat/core/strides.cpython-39-i386-linux-gnu.so
fastmat/core/types.cpython-39-i386-linux-gnu.so
fastmat/algorithms/__init__.py
fastmat/algorithms/FISTA.py
fastmat/algorithms/ISTA.py
fastmat/algorithms/STELA.py
fastmat/algorithms/Algorithm.cpython-39-i386-linux-gnu.so
fastmat/algorithms/OMP.cpython-39-i386-linux-gnu.so
fastmat/inspect/__init__.py
fastmat/inspect/common.py
fastmat/inspect/test.py
fastmat/inspect/benchmark.py
